LICENSE
MANIFEST.in
README.rst
requirements.txt
setup.py
django_pages_cms.egg-info/PKG-INFO
django_pages_cms.egg-info/SOURCES.txt
django_pages_cms.egg-info/dependency_links.txt
django_pages_cms.egg-info/not-zip-safe
django_pages_cms.egg-info/requires.txt
django_pages_cms.egg-info/top_level.txt
docs/FIXME
docs/TODO
docs/installation.rst
docs/usage.rst
docs/example_app/__init__.py
docs/example_app/manage.py
docs/example_app/requirements.txt
docs/example_app/example_app/__init__.py
docs/example_app/example_app/settings.py
docs/example_app/example_app/urls.py
docs/example_app/example_app/wsgi.py
docs/example_app/extpages/__init__.py
docs/example_app/extpages/admin/__init__.py
docs/example_app/extpages/admin/pagevideocontent.py
docs/example_app/extpages/fixtures/ext_content_types.yaml
docs/example_app/extpages/migrations/0001_initial.py
docs/example_app/extpages/migrations/__init__.py
docs/example_app/extpages/models/__init__.py
docs/example_app/extpages/models/pagevideocontent.py
docs/example_app/extpages/templatetags/__init__.py
docs/example_app/extpages/templatetags/extpages_tags.py
docs/example_app/templates/pages/pages/page.html
docs/example_app/web/media/pages/.keep
docs/example_app/web/static/.keep
pages/__init__.py
pages/cache.py
pages/conf.py
pages/urls.py
pages/admin/__init__.py
pages/admin/page.py
pages/admin/pagecontent.py
pages/admin/pagecontenttype.py
pages/admin/pagecontenttypes.py
pages/admin/pagedefaultcontent.py
pages/fixtures/content_types.yaml
pages/managers/__init__.py
pages/managers/contenttypemanager.py
pages/managers/pagemanager.py
pages/migrations/0001_initial.py
pages/migrations/0002_page_default_content.py
pages/migrations/__init__.py
pages/models/__init__.py
pages/models/page.py
pages/models/pagebasecontent.py
pages/models/pagecontent.py
pages/models/pagecontenttype.py
pages/models/pagecontenttypes.py
pages/models/pagedefaultcontent.py
pages/static/.keep
pages/templates/admin/pages/page/change_form.html
pages/templates/pages/403.html
pages/templates/pages/page.html
pages/templatetags/__init__.py
pages/templatetags/pages_tags.py
pages/tests/__init__.py
pages/tests/base.py
pages/tests/runtests.py
pages/tests/test_pages.py
pages/tests/test_settings.py
pages/tests/urls.py
